LICENSE
MANIFEST.in
README.md
setup.py
greenbyteapi/__init__.py
greenbyteapi/api_helper.py
greenbyteapi/configuration.py
greenbyteapi/decorators.py
greenbyteapi/greenbyteapi_client.py
greenbyteapi.egg-info/PKG-INFO
greenbyteapi.egg-info/SOURCES.txt
greenbyteapi.egg-info/dependency_links.txt
greenbyteapi.egg-info/requires.txt
greenbyteapi.egg-info/top_level.txt
greenbyteapi/controllers/__init__.py
greenbyteapi/controllers/alerts_controller.py
greenbyteapi/controllers/assets_controller.py
greenbyteapi/controllers/base_controller.py
greenbyteapi/controllers/configuration_data_controller.py
greenbyteapi/controllers/data_controller.py
greenbyteapi/controllers/plan_controller.py
greenbyteapi/controllers/predict_controller.py
greenbyteapi/controllers/statuses_controller.py
greenbyteapi/exceptions/__init__.py
greenbyteapi/exceptions/api_exception.py
greenbyteapi/exceptions/problem_details_exception.py
greenbyteapi/http/__init__.py
greenbyteapi/http/http_call_back.py
greenbyteapi/http/http_client.py
greenbyteapi/http/http_context.py
greenbyteapi/http/http_method_enum.py
greenbyteapi/http/http_request.py
greenbyteapi/http/http_response.py
greenbyteapi/http/requests_client.py
greenbyteapi/http/auth/__init__.py
greenbyteapi/http/auth/custom_header_auth.py
greenbyteapi/models/__init__.py
greenbyteapi/models/aggregate_mode_enum.py
greenbyteapi/models/alert_item.py
greenbyteapi/models/assignee.py
greenbyteapi/models/calculation_mode_enum.py
greenbyteapi/models/calculation_mode_real_time_enum.py
greenbyteapi/models/category_time_enum.py
greenbyteapi/models/client_configuration.py
greenbyteapi/models/component.py
greenbyteapi/models/configuration_item.py
greenbyteapi/models/contract_type_enum.py
greenbyteapi/models/data_item.py
greenbyteapi/models/data_per_category_item.py
greenbyteapi/models/data_per_category_response.py
greenbyteapi/models/data_real_time_item.py
greenbyteapi/models/data_signal.py
greenbyteapi/models/data_signal_configuration.py
greenbyteapi/models/data_signal_item.py
greenbyteapi/models/device.py
greenbyteapi/models/device_access.py
greenbyteapi/models/device_model.py
greenbyteapi/models/device_type.py
