Metadata-Version: 2.1
Name: greenbyteapi
Version: 2.2.5
Summary: Python client library for Greenbyte API
Home-page: https://apimatic.io
Author: APIMatic SDK Generator
Author-email: support@apimatic.io
License-File: LICENSE
